{
  "extraction_date": "2026-07-04",
  "total_articles": 23,
  "language_stats": {
    "total_articles": 23,
    "language_distribution": {
      "hi": {
        "count": 6,
        "percentage": 26.09
      },
      "en": {
        "count": 12,
        "percentage": 52.17
      },
      "gu": {
        "count": 4,
        "percentage": 17.39
      },
      "bn": {
        "count": 1,
        "percentage": 4.35
      }
    }
  },
  "quality_breakdown": {
    "high": 15,
    "medium": 6,
    "low": 2
  },
  "region_breakdown": {
    "delhi": 2,
    "jammu-and-kashmir": 1,
    "bihar": 1,
    "telangana": 1,
    "gujarat": 4,
    "jharkhand": 3,
    "nagaland": 1,
    "odisha": 3,
    "maharashtra": 1,
    "goa": 1,
    "assam": 1,
    "himachal-pradesh": 2,
    "arunachal-pradesh": 1,
    "tripura": 1
  },
  "disaster_breakdown": {
    "Monsoon": 23
  },
  "extraction_timestamp": "2026-07-04 13:28:39"
}