{
  "extraction_date": "2025-08-07",
  "total_articles": 136,
  "language_stats": {
    "total_articles": 136,
    "language_distribution": {
      "ta": {
        "count": 2,
        "percentage": 1.47
      },
      "en": {
        "count": 95,
        "percentage": 69.85
      },
      "hi": {
        "count": 31,
        "percentage": 22.79
      },
      "bn": {
        "count": 6,
        "percentage": 4.41
      },
      "gu": {
        "count": 2,
        "percentage": 1.47
      }
    }
  },
  "quality_breakdown": {
    "high": 101,
    "medium": 27,
    "low": 8
  },
  "region_breakdown": {
    "tamil-nadu": 6,
    "rajasthan": 3,
    "odisha": 1,
    "karnataka": 7,
    "uttarakhand": 14,
    "uttar-pradesh": 14,
    "tripura": 4,
    "andhra-pradesh": 3,
    "jharkhand": 1,
    "west-bengal": 6,
    "haryana": 4,
    "mizoram": 1,
    "madhya-pradesh": 3,
    "chhattisgarh": 1,
    "arunachal-pradesh": 1,
    "manipur": 2,
    "bihar": 10,
    "kerala": 2,
    "goa": 2,
    "maharashtra": 7,
    "assam": 1,
    "nagaland": 2,
    "meghalaya": 2,
    "himachal-pradesh": 8,
    "gujarat": 4,
    "telangana": 5,
    "punjab": 2,
    "chandigarh": 6,
    "delhi": 11,
    "ladakh": 1,
    "jammu-and-kashmir": 2
  },
  "disaster_breakdown": {
    "Monsoon": 136
  },
  "extraction_timestamp": "2025-08-07 11:48:40"
}